{
  "match_id": 85695,
  "slug": "rare-atom-vs-hotu-31-03-2025",
  "bo_type": 3,
  "team1_id": 2506,
  "team2_id": 2720,
  "team1_name": "Rare Atom",
  "team2_name": "HOTU",
  "team1_score": 0,
  "team2_score": 2,
  "winner_team": "HOTU",
  "games": [
    {
      "number": 2,
      "map_name": "de_ancient",
      "map_id": 125051,
      "rounds_count": 18,
      "winner_team_id": 2720,
      "loser_team_id": 2506,
      "winner_score": 13,
      "loser_score": 5,
      "begin_at": "2025-03-31T06:38:10.000+00:00",
      "status": "finished",
      "player_stats": []
    },
    {
      "number": 1,
      "map_name": "de_mirage",
      "map_id": 125052,
      "rounds_count": 18,
      "winner_team_id": 2720,
      "loser_team_id": 2506,
      "winner_score": 13,
      "loser_score": 5,
      "begin_at": "2025-03-31T05:25:50.000+00:00",
      "status": "finished",
      "player_stats": []
    }
  ],
  "tournament_id": "4313",
  "tournament_name": "PGL Astana 2025: Asian Qualifier",
  "scrape_date": "2025-03-31"
}