{
  "match_id": 80640,
  "slug": "swingers-vs-mibr-academy-14-02-2025",
  "bo_type": 3,
  "team1_id": 5297,
  "team2_id": 2239,
  "team1_name": "Swingers",
  "team2_name": "MIBR Academy",
  "team1_score": 2,
  "team2_score": 0,
  "winner_team": "Swingers",
  "games": [
    {
      "number": 2,
      "map_name": "de_dust2",
      "map_id": 118752,
      "rounds_count": 17,
      "winner_team_id": 5297,
      "loser_team_id": 2239,
      "winner_score": 13,
      "loser_score": 4,
      "begin_at": "2025-02-14T02:38:51.000+00:00",
      "status": "finished",
      "state": "done",
      "player_stats": [
        {
          "id": 1410088,
          "game_id": 118752,
          "steam_profile_id": 13276,
          "steam_profile_player_id": 37412,
          "steam_profile_nickname": "stormzyn",
          "steam_profile_player_slug": "-stormzin",
          "clan_name": "MIBR Academy",
          "team_id": 2239,
          "enemy_clan_name": "Swingers",
          "kills": 4,
          "death": 15,
          "assists": 3,
          "headshots": 4,
          "adr": 49.11764705882353,
          "kast": 0.4117647058823529,
          "player_rating": 3.7231959018641874,
          "first_kills": 0,
          "first_death": 3,
          "trade_kills": 0,
          "trade_death": 2,
          "multikills_2k": 0,
          "multikills_3k": 0,
          "multikills_4k": 0,
          "multikills_5k": 0,
          "multikill_score": 0,
          "opening_duels": 3,
          "opening_kill_success_rate": 0.0,
          "traded_death_rate": 0.13333333333333333,
          "money_spent": 4500,
          "money_save": 4000,
          "utility_value": 1950,
          "total_equipment_value": 48150,
          "additional_value": 10000,
          "clutch_successes": 0,
          "clutch_attempts": 1,
          "clutch_success_rate": 0.0,
          "entry_kills": 0,
          "entry_deaths": 1,
          "entry_kill_ratio": 0.0,
          "plants": 0,
          "plant_attempts": 1,
          "plant_success_rate": 0.0,
          "kd_ratio": 0.26666666666666666,
          "headshot_percentage": 1.0,
          "is_awper": false,
          "is_igl": false
        },
        {
          "id": 1410089,
          "game_id": 118752,
          "steam_profile_id": 936,
          "steam_profile_player_id": 27966,
          "steam_profile_nickname": "★ ⑳ ninjaZ",
          "steam_profile_player_slug": "ninjaz4n",
          "clan_name": "Swingers",
          "team_id": 5297,
          "enemy_clan_name": "MIBR Academy",
          "kills": 6,
          "death": 8,
          "assists": 9,
          "headshots": 1,
          "adr": 63.11764705882353,
          "kast": 0.8235294117647058,
          "player_rating": 4.8849488027848285,
          "first_kills": 1,
          "first_death": 3,
          "trade_kills": 1,
          "trade_death": 2,
          "multikills_2k": 0,
          "multikills_3k": 1,
          "multikills_4k": 0,
          "multikills_5k": 0,
          "multikill_score": 3,
          "opening_duels": 4,
          "opening_kill_success_rate": 0.25,
          "traded_death_rate": 0.25,
          "money_spent": 17850,
          "money_save": 34450,
          "utility_value": 3500,
          "total_equipment_value": 69050,
          "additional_value": 15700,
          "clutch_successes": 0,
          "clutch_attempts": 1,
          "clutch_success_rate": 0.0,
          "entry_kills": 0,
          "entry_deaths": 1,
          "entry_kill_ratio": 0.0,
          "plants": 0,
          "plant_attempts": 1,
          "plant_success_rate": 0.0,
          "kd_ratio": 0.75,
          "headshot_percentage": 0.16666666666666666,
          "is_awper": false,
          "is_igl": false
        },
        {
          "id": 1410090,
          "game_id": 118752,
          "steam_profile_id": 1125,
          "steam_profile_player_id": 27429,
          "steam_profile_nickname": "★ ⑳ desh    *NOPING",
          "steam_profile_player_slug": "desh",
          "clan_name": "Swingers",
          "team_id": 5297,
          "enemy_clan_name": "MIBR Academy",
          "kills": 26,
          "death": 6,
          "assists": 6,
          "headshots": 7,
          "adr": 143.23529411764707,
          "kast": 0.8235294117647058,
          "player_rating": 10.0,
          "first_kills": 5,
          "first_death": 0,
          "trade_kills": 3,
          "trade_death": 1,
          "multikills_2k": 5,
          "multikills_3k": 2,
          "multikills_4k": 1,
          "multikills_5k": 0,
          "multikill_score": 20,
          "opening_duels": 5,
          "opening_kill_success_rate": 1.0,
          "traded_death_rate": 0.16666666666666666,
          "money_spent": 29950,
          "money_save": 52850,
          "utility_value": 2400,
          "total_equipment_value": 86150,
          "additional_value": 13000,
          "clutch_successes": 0,
          "clutch_attempts": 1,
          "clutch_success_rate": 0.0,
          "entry_kills": 0,
          "entry_deaths": 1,
          "entry_kill_ratio": 0.0,
          "plants": 0,
          "plant_attempts": 1,
          "plant_success_rate": 0.0,
          "kd_ratio": 4.333333333333333,
          "headshot_percentage": 0.2692307692307692,
          "is_awper": false,
          "is_igl": false
        },
        {
          "id": 1410091,
          "game_id": 118752,
          "steam_profile_id": 2132,
          "steam_profile_player_id": 28819,
          "steam_profile_nickname": "card",
          "steam_profile_player_slug": "card",
          "clan_name": "MIBR Academy",
          "team_id": 2239,
          "enemy_clan_name": "Swingers",
          "kills": 5,
          "death": 16,
          "assists": 2,
          "headshots": 2,
          "adr": 45.64705882352941,
          "kast": 0.47058823529411764,
          "player_rating": 3.913301971505756,
          "first_kills": 0,
          "first_death": 1,
          "trade_kills": 2,
          "trade_death": 2,
          "multikills_2k": 1,
          "multikills_3k": 0,
          "multikills_4k": 0,
          "multikills_5k": 0,
          "multikill_score": 2,
          "opening_duels": 1,
          "opening_kill_success_rate": 0.0,
          "traded_death_rate": 0.125,
          "money_spent": 2100,
          "money_save": 6350,
          "utility_value": 1800,
          "total_equipment_value": 54600,
          "additional_value": 9600,
          "clutch_successes": 0,
          "clutch_attempts": 1,
          "clutch_success_rate": 0.0,
          "entry_kills": 0,
          "entry_deaths": 1,
          "entry_kill_ratio": 0.0,
          "plants": 0,
          "plant_attempts": 1,
          "plant_success_rate": 0.0,
          "kd_ratio": 0.3125,
          "headshot_percentage": 0.4,
          "is_awper": false,
          "is_igl": false
        },
        {
          "id": 1410092,
          "game_id": 118752,
          "steam_profile_id": 3425,
          "steam_profile_player_id": 35434,
          "steam_profile_nickname": "★ ⑳ vinaabeast",
          "steam_profile_player_slug": "vinaabeast",
          "clan_name": "Swingers",
          "team_id": 5297,
          "enemy_clan_name": "MIBR Academy",
          "kills": 14,
          "death": 7,
          "assists": 4,
          "headshots": 5,
          "adr": 62.88235294117647,
          "kast": 0.8823529411764706,
          "player_rating": 6.316318221515908,
          "first_kills": 1,
          "first_death": 1,
          "trade_kills": 1,
          "trade_death": 0,
          "multikills_2k": 3,
          "multikills_3k": 0,
          "multikills_4k": 0,
          "multikills_5k": 0,
          "multikill_score": 6,
          "opening_duels": 2,
          "opening_kill_success_rate": 0.5,
          "traded_death_rate": 0.0,
          "money_spent": 26950,
          "money_save": 39000,
          "utility_value": 2700,
          "total_equipment_value": 75000,
          "additional_value": 17800,
          "clutch_successes": 0,
          "clutch_attempts": 1,
          "clutch_success_rate": 0.0,
          "entry_kills": 0,
          "entry_deaths": 1,
          "entry_kill_ratio": 0.0,
          "plants": 0,
          "plant_attempts": 1,
          "plant_success_rate": 0.0,
          "kd_ratio": 2.0,
          "headshot_percentage": 0.35714285714285715,
          "is_awper": false,
          "is_igl": false
        },
        {
          "id": 1410093,
          "game_id": 118752,
          "steam_profile_id": 1710,
          "steam_profile_player_id": 31542,
          "steam_profile_nickname": "★ ⑳ mlhzin",
          "steam_profile_player_slug": "mlhzin",
          "clan_name": "MIBR Academy",
          "team_id": 2239,
          "enemy_clan_name": "Swingers",
          "kills": 9,
          "death": 15,
          "assists": 1,
          "headshots": 6,
          "adr": 52.11764705882353,
          "kast": 0.4117647058823529,
          "player_rating": 4.409161598932274,
          "first_kills": 2,
          "first_death": 6,
          "trade_kills": 2,
          "trade_death": 2,
          "multikills_2k": 1,
          "multikills_3k": 1,
          "multikills_4k": 0,
          "multikills_5k": 0,
          "multikill_score": 5,
          "opening_duels": 8,
          "opening_kill_success_rate": 0.25,
          "traded_death_rate": 0.13333333333333333,
          "money_spent": 4350,
          "money_save": 4350,
          "utility_value": 1400,
          "total_equipment_value": 48100,
          "additional_value": 9550,
          "clutch_successes": 0,
          "clutch_attempts": 1,
          "clutch_success_rate": 0.0,
          "entry_kills": 0,
          "entry_deaths": 1,
          "entry_kill_ratio": 0.0,
          "plants": 0,
          "plant_attempts": 1,
          "plant_success_rate": 0.0,
          "kd_ratio": 0.6,
          "headshot_percentage": 0.6666666666666666,
          "is_awper": false,
          "is_igl": false
        },
        {
          "id": 1410094,
          "game_id": 118752,
          "steam_profile_id": 98,
          "steam_profile_player_id": 17747,
          "steam_profile_nickname": "leo_drunky",
          "steam_profile_player_slug": "leo_drunky",
          "clan_name": "Swingers",
          "team_id": 5297,
          "enemy_clan_name": "MIBR Academy",
          "kills": 18,
          "death": 8,
          "assists": 5,
          "headshots": 9,
          "adr": 92.76470588235294,
          "kast": 0.8235294117647058,
          "player_rating": 7.678638081117737,
          "first_kills": 2,
          "first_death": 0,
          "trade_kills": 1,
          "trade_death": 3,
          "multikills_2k": 3,
          "multikills_3k": 2,
          "multikills_4k": 1,
          "multikills_5k": 0,
          "multikill_score": 16,
          "opening_duels": 2,
          "opening_kill_success_rate": 1.0,
          "traded_death_rate": 0.375,
          "money_spent": 23000,
          "money_save": 39300,
          "utility_value": 2300,
          "total_equipment_value": 74150,
          "additional_value": 17800,
          "clutch_successes": 0,
          "clutch_attempts": 1,
          "clutch_success_rate": 0.0,
          "entry_kills": 0,
          "entry_deaths": 1,
          "entry_kill_ratio": 0.0,
          "plants": 0,
          "plant_attempts": 1,
          "plant_success_rate": 0.0,
          "kd_ratio": 2.25,
          "headshot_percentage": 0.5,
          "is_awper": false,
          "is_igl": false
        },
        {
          "id": 1410095,
          "game_id": 118752,
          "steam_profile_id": 2303,
          "steam_profile_player_id": 31831,
          "steam_profile_nickname": "★ ⑳ brn$ the coyote",
          "steam_profile_player_slug": "brn-bruno-araujo",
          "clan_name": "MIBR Academy",
          "team_id": 2239,
          "enemy_clan_name": "Swingers",
          "kills": 7,
          "death": 16,
          "assists": 2,
          "headshots": 3,
          "adr": 43.35294117647059,
          "kast": 0.5294117647058824,
          "player_rating": 4.199080896868696,
          "first_kills": 1,
          "first_death": 1,
          "trade_kills": 3,
          "trade_death": 1,
          "multikills_2k": 0,
          "multikills_3k": 0,
          "multikills_4k": 0,
          "multikills_5k": 0,
          "multikill_score": 0,
          "opening_duels": 2,
          "opening_kill_success_rate": 0.5,
          "traded_death_rate": 0.0625,
          "money_spent": 3500,
          "money_save": 4000,
          "utility_value": 1200,
          "total_equipment_value": 50050,
          "additional_value": 11650,
          "clutch_successes": 0,
          "clutch_attempts": 1,
          "clutch_success_rate": 0.0,
          "entry_kills": 0,
          "entry_deaths": 1,
          "entry_kill_ratio": 0.0,
          "plants": 0,
          "plant_attempts": 1,
          "plant_success_rate": 0.0,
          "kd_ratio": 0.4375,
          "headshot_percentage": 0.42857142857142855,
          "is_awper": false,
          "is_igl": false
        },
        {
          "id": 1410096,
          "game_id": 118752,
          "steam_profile_id": 14098,
          "steam_profile_player_id": 38277,
          "steam_profile_nickname": "pktRenanZin_",
          "steam_profile_player_slug": "renanzin",
          "clan_name": "MIBR Academy",
          "team_id": 2239,
          "enemy_clan_name": "Swingers",
          "kills": 9,
          "death": 14,
          "assists": 1,
          "headshots": 5,
          "adr": 62.705882352941174,
          "kast": 0.4117647058823529,
          "player_rating": 5.515570207416648,
          "first_kills": 2,
          "first_death": 1,
          "trade_kills": 1,
          "trade_death": 3,
          "multikills_2k": 1,
          "multikills_3k": 1,
          "multikills_4k": 0,
          "multikills_5k": 0,
          "multikill_score": 5,
          "opening_duels": 3,
          "opening_kill_success_rate": 0.6666666666666666,
          "traded_death_rate": 0.21428571428571427,
          "money_spent": 8950,
          "money_save": 10500,
          "utility_value": 1900,
          "total_equipment_value": 46950,
          "additional_value": 10250,
          "clutch_successes": 0,
          "clutch_attempts": 1,
          "clutch_success_rate": 0.0,
          "entry_kills": 0,
          "entry_deaths": 1,
          "entry_kill_ratio": 0.0,
          "plants": 0,
          "plant_attempts": 1,
          "plant_success_rate": 0.0,
          "kd_ratio": 0.6428571428571429,
          "headshot_percentage": 0.5555555555555556,
          "is_awper": false,
          "is_igl": false
        },
        {
          "id": 1410097,
          "game_id": 118752,
          "steam_profile_id": 899,
          "steam_profile_player_id": 26665,
          "steam_profile_nickname": "★ ⑳ ponter",
          "steam_profile_player_slug": "ponter",
          "clan_name": "Swingers",
          "team_id": 5297,
          "enemy_clan_name": "MIBR Academy",
          "kills": 12,
          "death": 6,
          "assists": 9,
          "headshots": 6,
          "adr": 91.11764705882354,
          "kast": 0.8823529411764706,
          "player_rating": 7.057827599088217,
          "first_kills": 3,
          "first_death": 1,
          "trade_kills": 2,
          "trade_death": 2,
          "multikills_2k": 2,
          "multikills_3k": 1,
          "multikills_4k": 0,
          "multikills_5k": 0,
          "multikill_score": 7,
          "opening_duels": 4,
          "opening_kill_success_rate": 0.75,
          "traded_death_rate": 0.3333333333333333,
          "money_spent": 26500,
          "money_save": 40250,
          "utility_value": 2900,
          "total_equipment_value": 73800,
          "additional_value": 15250,
          "clutch_successes": 0,
          "clutch_attempts": 1,
          "clutch_success_rate": 0.0,
          "entry_kills": 0,
          "entry_deaths": 1,
          "entry_kill_ratio": 0.0,
          "plants": 0,
          "plant_attempts": 1,
          "plant_success_rate": 0.0,
          "kd_ratio": 2.0,
          "headshot_percentage": 0.5,
          "is_awper": false,
          "is_igl": false
        }
      ]
    },
    {
      "number": 1,
      "map_name": "de_ancient",
      "map_id": 118753,
      "rounds_count": 41,
      "winner_team_id": 5297,
      "loser_team_id": 2239,
      "winner_score": 22,
      "loser_score": 19,
      "begin_at": "2025-02-14T00:49:26.000+00:00",
      "status": "finished",
      "state": "done",
      "player_stats": [
        {
          "id": 1410078,
          "game_id": 118753,
          "steam_profile_id": 936,
          "steam_profile_player_id": 27966,
          "steam_profile_nickname": "★ ⑳ ninjaZ",
          "steam_profile_player_slug": "ninjaz4n",
          "clan_name": "Swingers",
          "team_id": 5297,
          "enemy_clan_name": "MIBR Academy",
          "kills": 30,
          "death": 29,
          "assists": 5,
          "headshots": 19,
          "adr": 75.90243902439025,
          "kast": 0.6829268292682927,
          "player_rating": 5.9251467227867245,
          "first_kills": 5,
          "first_death": 8,
          "trade_kills": 6,
          "trade_death": 5,
          "multikills_2k": 8,
          "multikills_3k": 1,
          "multikills_4k": 0,
          "multikills_5k": 0,
          "multikill_score": 19,
          "opening_duels": 13,
          "opening_kill_success_rate": 0.38461538461538464,
          "traded_death_rate": 0.1724137931034483,
          "money_spent": 45300,
          "money_save": 32950,
          "utility_value": 7800,
          "total_equipment_value": 187550,
          "additional_value": 41600,
          "clutch_successes": 0,
          "clutch_attempts": 1,
          "clutch_success_rate": 0.0,
          "entry_kills": 0,
          "entry_deaths": 1,
          "entry_kill_ratio": 0.0,
          "plants": 0,
          "plant_attempts": 1,
          "plant_success_rate": 0.0,
          "kd_ratio": 1.0344827586206897,
          "headshot_percentage": 0.6333333333333333,
          "is_awper": false,
          "is_igl": false
        },
        {
          "id": 1410079,
          "game_id": 118753,
          "steam_profile_id": 3425,
          "steam_profile_player_id": 35434,
          "steam_profile_nickname": "★ ⑳ vinaabeast",
          "steam_profile_player_slug": "vinaabeast",
          "clan_name": "Swingers",
          "team_id": 5297,
          "enemy_clan_name": "MIBR Academy",
          "kills": 30,
          "death": 30,
          "assists": 13,
          "headshots": 16,
          "adr": 93.29268292682927,
          "kast": 0.7560975609756098,
          "player_rating": 6.674328072706389,
          "first_kills": 2,
          "first_death": 1,
          "trade_kills": 7,
          "trade_death": 8,
          "multikills_2k": 3,
          "multikills_3k": 3,
          "multikills_4k": 0,
          "multikills_5k": 0,
          "multikill_score": 15,
          "opening_duels": 3,
          "opening_kill_success_rate": 0.6666666666666666,
          "traded_death_rate": 0.26666666666666666,
          "money_spent": 47900,
          "money_save": 30000,
          "utility_value": 6700,
          "total_equipment_value": 185250,
          "additional_value": 41450,
          "clutch_successes": 0,
          "clutch_attempts": 1,
          "clutch_success_rate": 0.0,
          "entry_kills": 0,
          "entry_deaths": 1,
          "entry_kill_ratio": 0.0,
          "plants": 0,
          "plant_attempts": 1,
          "plant_success_rate": 0.0,
          "kd_ratio": 1.0,
          "headshot_percentage": 0.5333333333333333,
          "is_awper": false,
          "is_igl": false
        },
        {
          "id": 1410080,
          "game_id": 118753,
          "steam_profile_id": 14098,
          "steam_profile_player_id": 38277,
          "steam_profile_nickname": "pktRenanZin_",
          "steam_profile_player_slug": "renanzin",
          "clan_name": "MIBR Academy",
          "team_id": 2239,
          "enemy_clan_name": "Swingers",
          "kills": 24,
          "death": 34,
          "assists": 11,
          "headshots": 11,
          "adr": 65.97560975609755,
          "kast": 0.6829268292682927,
          "player_rating": 5.448383770758845,
          "first_kills": 3,
          "first_death": 2,
          "trade_kills": 4,
          "trade_death": 7,
          "multikills_2k": 3,
          "multikills_3k": 1,
          "multikills_4k": 0,
          "multikills_5k": 0,
          "multikill_score": 9,
          "opening_duels": 5,
          "opening_kill_success_rate": 0.6,
          "traded_death_rate": 0.20588235294117646,
          "money_spent": 24150,
          "money_save": 21750,
          "utility_value": 6000,
          "total_equipment_value": 180250,
          "additional_value": 34600,
          "clutch_successes": 0,
          "clutch_attempts": 1,
          "clutch_success_rate": 0.0,
          "entry_kills": 0,
          "entry_deaths": 1,
          "entry_kill_ratio": 0.0,
          "plants": 0,
          "plant_attempts": 1,
          "plant_success_rate": 0.0,
          "kd_ratio": 0.7058823529411765,
          "headshot_percentage": 0.4583333333333333,
          "is_awper": false,
          "is_igl": false
        },
        {
          "id": 1410081,
          "game_id": 118753,
          "steam_profile_id": 2303,
          "steam_profile_player_id": 31831,
          "steam_profile_nickname": "★ ⑳ brn$ the coyote",
          "steam_profile_player_slug": "brn-bruno-araujo",
          "clan_name": "MIBR Academy",
          "team_id": 2239,
          "enemy_clan_name": "Swingers",
          "kills": 36,
          "death": 26,
          "assists": 7,
          "headshots": 11,
          "adr": 87.17073170731707,
          "kast": 0.7317073170731707,
          "player_rating": 6.822931063266253,
          "first_kills": 2,
          "first_death": 2,
          "trade_kills": 7,
          "trade_death": 5,
          "multikills_2k": 5,
          "multikills_3k": 1,
          "multikills_4k": 2,
          "multikills_5k": 0,
          "multikill_score": 21,
          "opening_duels": 4,
          "opening_kill_success_rate": 0.5,
          "traded_death_rate": 0.19230769230769232,
          "money_spent": 59750,
          "money_save": 66500,
          "utility_value": 5300,
          "total_equipment_value": 194150,
          "additional_value": 41950,
          "clutch_successes": 0,
          "clutch_attempts": 1,
          "clutch_success_rate": 0.0,
          "entry_kills": 0,
          "entry_deaths": 1,
          "entry_kill_ratio": 0.0,
          "plants": 0,
          "plant_attempts": 1,
          "plant_success_rate": 0.0,
          "kd_ratio": 1.3846153846153846,
          "headshot_percentage": 0.3055555555555556,
          "is_awper": false,
          "is_igl": false
        },
        {
          "id": 1410082,
          "game_id": 118753,
          "steam_profile_id": 13276,
          "steam_profile_player_id": 37412,
          "steam_profile_nickname": "stormzyn",
          "steam_profile_player_slug": "-stormzin",
          "clan_name": "MIBR Academy",
          "team_id": 2239,
          "enemy_clan_name": "Swingers",
          "kills": 31,
          "death": 31,
          "assists": 9,
          "headshots": 13,
          "adr": 89.0,
          "kast": 0.6097560975609756,
          "player_rating": 6.052546197105236,
          "first_kills": 3,
          "first_death": 6,
          "trade_kills": 6,
          "trade_death": 2,
          "multikills_2k": 8,
          "multikills_3k": 1,
          "multikills_4k": 0,
          "multikills_5k": 0,
          "multikill_score": 19,
          "opening_duels": 9,
          "opening_kill_success_rate": 0.3333333333333333,
          "traded_death_rate": 0.06451612903225806,
          "money_spent": 39350,
          "money_save": 41900,
          "utility_value": 6500,
          "total_equipment_value": 190250,
          "additional_value": 41100,
          "clutch_successes": 0,
          "clutch_attempts": 1,
          "clutch_success_rate": 0.0,
          "entry_kills": 0,
          "entry_deaths": 1,
          "entry_kill_ratio": 0.0,
          "plants": 0,
          "plant_attempts": 1,
          "plant_success_rate": 0.0,
          "kd_ratio": 1.0,
          "headshot_percentage": 0.41935483870967744,
          "is_awper": false,
          "is_igl": false
        },
        {
          "id": 1410083,
          "game_id": 118753,
          "steam_profile_id": 98,
          "steam_profile_player_id": 17747,
          "steam_profile_nickname": "leo_drunky",
          "steam_profile_player_slug": "leo_drunky",
          "clan_name": "Swingers",
          "team_id": 5297,
          "enemy_clan_name": "MIBR Academy",
          "kills": 28,
          "death": 32,
          "assists": 15,
          "headshots": 16,
          "adr": 79.02439024390245,
          "kast": 0.8048780487804879,
          "player_rating": 6.171630201983511,
          "first_kills": 5,
          "first_death": 6,
          "trade_kills": 9,
          "trade_death": 10,
          "multikills_2k": 4,
          "multikills_3k": 1,
          "multikills_4k": 1,
          "multikills_5k": 0,
          "multikill_score": 15,
          "opening_duels": 11,
          "opening_kill_success_rate": 0.45454545454545453,
          "traded_death_rate": 0.3125,
          "money_spent": 31000,
          "money_save": 34750,
          "utility_value": 6700,
          "total_equipment_value": 187850,
          "additional_value": 42350,
          "clutch_successes": 0,
          "clutch_attempts": 1,
          "clutch_success_rate": 0.0,
          "entry_kills": 0,
          "entry_deaths": 1,
          "entry_kill_ratio": 0.0,
          "plants": 0,
          "plant_attempts": 1,
          "plant_success_rate": 0.0,
          "kd_ratio": 0.875,
          "headshot_percentage": 0.5714285714285714,
          "is_awper": false,
          "is_igl": false
        },
        {
          "id": 1410084,
          "game_id": 118753,
          "steam_profile_id": 1710,
          "steam_profile_player_id": 31542,
          "steam_profile_nickname": "★ ⑳ mlhzin",
          "steam_profile_player_slug": "mlhzin",
          "clan_name": "MIBR Academy",
          "team_id": 2239,
          "enemy_clan_name": "Swingers",
          "kills": 29,
          "death": 33,
          "assists": 9,
          "headshots": 14,
          "adr": 80.60975609756098,
          "kast": 0.7317073170731707,
          "player_rating": 6.131742875195567,
          "first_kills": 8,
          "first_death": 8,
          "trade_kills": 3,
          "trade_death": 7,
          "multikills_2k": 4,
          "multikills_3k": 2,
          "multikills_4k": 0,
          "multikills_5k": 0,
          "multikill_score": 14,
          "opening_duels": 16,
          "opening_kill_success_rate": 0.5,
          "traded_death_rate": 0.21212121212121213,
          "money_spent": 28750,
          "money_save": 27400,
          "utility_value": 8200,
          "total_equipment_value": 192650,
          "additional_value": 42250,
          "clutch_successes": 0,
          "clutch_attempts": 1,
          "clutch_success_rate": 0.0,
          "entry_kills": 0,
          "entry_deaths": 1,
          "entry_kill_ratio": 0.0,
          "plants": 0,
          "plant_attempts": 1,
          "plant_success_rate": 0.0,
          "kd_ratio": 0.8787878787878788,
          "headshot_percentage": 0.4827586206896552,
          "is_awper": false,
          "is_igl": false
        },
        {
          "id": 1410085,
          "game_id": 118753,
          "steam_profile_id": 1125,
          "steam_profile_player_id": 27429,
          "steam_profile_nickname": "★ ⑳ desh    *NOPING",
          "steam_profile_player_slug": "desh",
          "clan_name": "Swingers",
          "team_id": 5297,
          "enemy_clan_name": "MIBR Academy",
          "kills": 25,
          "death": 27,
          "assists": 7,
          "headshots": 4,
          "adr": 49.829268292682926,
          "kast": 0.7073170731707317,
          "player_rating": 5.5291432900590225,
          "first_kills": 2,
          "first_death": 1,
          "trade_kills": 4,
          "trade_death": 5,
          "multikills_2k": 7,
          "multikills_3k": 0,
          "multikills_4k": 0,
          "multikills_5k": 0,
          "multikill_score": 14,
          "opening_duels": 3,
          "opening_kill_success_rate": 0.6666666666666666,
          "traded_death_rate": 0.18518518518518517,
          "money_spent": 46950,
          "money_save": 62000,
          "utility_value": 5600,
          "total_equipment_value": 236950,
          "additional_value": 38050,
          "clutch_successes": 0,
          "clutch_attempts": 1,
          "clutch_success_rate": 0.0,
          "entry_kills": 0,
          "entry_deaths": 1,
          "entry_kill_ratio": 0.0,
          "plants": 0,
          "plant_attempts": 1,
          "plant_success_rate": 0.0,
          "kd_ratio": 0.9259259259259259,
          "headshot_percentage": 0.16,
          "is_awper": false,
          "is_igl": false
        },
        {
          "id": 1410086,
          "game_id": 118753,
          "steam_profile_id": 899,
          "steam_profile_player_id": 26665,
          "steam_profile_nickname": "★ ⑳ ponter",
          "steam_profile_player_slug": "ponter",
          "clan_name": "Swingers",
          "team_id": 5297,
          "enemy_clan_name": "MIBR Academy",
          "kills": 36,
          "death": 32,
          "assists": 12,
          "headshots": 25,
          "adr": 97.0,
          "kast": 0.7073170731707317,
          "player_rating": 7.167653602175061,
          "first_kills": 6,
          "first_death": 5,
          "trade_kills": 6,
          "trade_death": 7,
          "multikills_2k": 3,
          "multikills_3k": 2,
          "multikills_4k": 3,
          "multikills_5k": 0,
          "multikill_score": 24,
          "opening_duels": 11,
          "opening_kill_success_rate": 0.5454545454545454,
          "traded_death_rate": 0.21875,
          "money_spent": 40750,
          "money_save": 42650,
          "utility_value": 7000,
          "total_equipment_value": 186050,
          "additional_value": 40850,
          "clutch_successes": 0,
          "clutch_attempts": 1,
          "clutch_success_rate": 0.0,
          "entry_kills": 0,
          "entry_deaths": 1,
          "entry_kill_ratio": 0.0,
          "plants": 0,
          "plant_attempts": 1,
          "plant_success_rate": 0.0,
          "kd_ratio": 1.125,
          "headshot_percentage": 0.6944444444444444,
          "is_awper": false,
          "is_igl": false
        },
        {
          "id": 1410087,
          "game_id": 118753,
          "steam_profile_id": 2132,
          "steam_profile_player_id": 28819,
          "steam_profile_nickname": "card",
          "steam_profile_player_slug": "card",
          "clan_name": "MIBR Academy",
          "team_id": 2239,
          "enemy_clan_name": "Swingers",
          "kills": 26,
          "death": 29,
          "assists": 9,
          "headshots": 8,
          "adr": 63.390243902439025,
          "kast": 0.7317073170731707,
          "player_rating": 6.025088346587057,
          "first_kills": 5,
          "first_death": 2,
          "trade_kills": 4,
          "trade_death": 5,
          "multikills_2k": 5,
          "multikills_3k": 0,
          "multikills_4k": 0,
          "multikills_5k": 0,
          "multikill_score": 10,
          "opening_duels": 7,
          "opening_kill_success_rate": 0.7142857142857143,
          "traded_death_rate": 0.1724137931034483,
          "money_spent": 40100,
          "money_save": 57400,
          "utility_value": 4600,
          "total_equipment_value": 238200,
          "additional_value": 39650,
          "clutch_successes": 0,
          "clutch_attempts": 1,
          "clutch_success_rate": 0.0,
          "entry_kills": 0,
          "entry_deaths": 1,
          "entry_kill_ratio": 0.0,
          "plants": 0,
          "plant_attempts": 1,
          "plant_success_rate": 0.0,
          "kd_ratio": 0.896551724137931,
          "headshot_percentage": 0.3076923076923077,
          "is_awper": false,
          "is_igl": false
        }
      ]
    }
  ],
  "tournament_id": "3746",
  "tournament_name": "CCT Season 2 South American Series 7",
  "scrape_date": "2025-02-14"
}